HelloPythonBittuKumar/__init__.py
HelloPythonBittuKumar/hello.py
HelloPythonBittuKumar/version.py
hellopythonbittukumar-0.1.0.dist-info/licenses/LICENSE
hellopythonbittukumar-0.1.0.dist-info/METADATA
hellopythonbittukumar-0.1.0.dist-info/WHEEL
hellopythonbittukumar-0.1.0.dist-info/top_level.txt
hellopythonbittukumar-0.1.0.dist-info/RECORD
