Metadata-Version: 2.4
Name: HelloPythonBittuKumar
Version: 0.1.0
Summary: A detailed HelloPython package
Author-email: BITTU KUMAR <bittukumar@gmail.com>
License-Expression: MIT
Project-URL: Homepage, https://github.com/KUMAR7BITTU
Requires-Python: >=3.7
License-File: LICENSE
Dynamic: license-file
